pytket_qirpass/__init__.py
pytket_qirpass/apply_qirpass.py
pytket_qirpass/qir_to_pytket.py
pytket_qirpass/utils.py
pytket_qirpass-0.10.0.dist-info/LICENSE
pytket_qirpass-0.10.0.dist-info/WHEEL
pytket_qirpass-0.10.0.dist-info/METADATA
pytket_qirpass-0.10.0.dist-info/RECORD
