Metadata-Version: 2.3
Name: pytket-qirpass
Version: 0.10.0
Summary: Module for optimizing QIR using pytket.
Author-email: Alec Edgington <alec.edgington@quantinuum.com>
Classifier: License :: OSI Approved :: Apache Software License
Requires-Dist: llvmlite >= 0.44.0
Requires-Dist: pytket >= 1.39.0
Requires-Dist: pyqir >=0.10.6 ; extra == "tests"
Project-URL: Home, https://github.com/CQCL/pytket-qirpass
Provides-Extra: tests
